noise_generator/lfsr_noise_gen.v
`timescale 1ns / 1ps

module lfsr_noise_gen #(
    parameter DATA_WIDTH = 16,     // Output width (misal 16-bit)
    parameter SEED       = 32'hACE1_2345 // Seed tidak boleh 0
)(
    input  wire clk,
    input  wire rst_n,
    input  wire enable,
    output wire [DATA_WIDTH-1:0] noise_out,
    output reg  valid_out
);

    // Gunakan internal register 32-bit agar periode randomness sangat panjang
    // (2^32 - 1 cycles sebelum berulang), meskipun outputnya cuma 16-bit.
    reg [31:0] r_lfsr;
    
    // Polinomial Galois untuk 32-bit: x^32 + x^22 + x^2 + x^1 + 1
    // Taps hex: 0x80200003
    localparam [31:0] POLY_MASK = 32'h80200003;

    always @(posedge clk or negedge rst_n) begin
        if (!rst_n) begin
            r_lfsr    <= SEED; 
            valid_out <= 0;
        end else if (enable) begin
            valid_out <= 1;
            
            // Galois LFSR Implementation
            // Jika LSB adalah 1, shift dan XOR dengan mask.
            // Jika LSB adalah 0, cukup shift.
            if (r_lfsr[0] == 1'b1) begin
                r_lfsr <= (r_lfsr >> 1) ^ POLY_MASK; 
            end else begin
                r_lfsr <= (r_lfsr >> 1);
            end
        end else begin
            valid_out <= 0;
        end
    end
    
    // OUTPUT MAPPING
    // Ambil bit-bit teratas (MSB) untuk kualitas randomness terbaik.
    // Jika DATA_WIDTH = 16, kita ambil r_lfsr[31:16]
    generate
        if (DATA_WIDTH < 32) begin
            assign noise_out = r_lfsr[31 : 32-DATA_WIDTH];
        end else begin
            // Jika output butuh > 32 bit, padding dengan 0 atau duplikasi (jarang terjadi)
            assign noise_out = { {(DATA_WIDTH-32){1'b0}}, r_lfsr };
        end
    endgenerate

endmodule

noise_generator/noise_matrix_filler.v
`include "lfsr_noise_gen.v"

module noise_matrix_filler #(
    parameter DATA_WIDTH = 16, // Ubah default ke 16 sesuai spesifikasi [-2, 2]
    parameter ADDR_WIDTH = 14 
)(
    input wire clk,
    input wire rst_n,
    input wire start,
    input wire [2:0] size,
    
    output reg [ADDR_WIDTH-1:0] bram_addr,
    output wire [DATA_WIDTH-1:0] bram_wdata,
    output wire bram_we,           
    
    output reg done
);

    // Internal Signals
    wire noise_valid;
    wire [DATA_WIDTH-1:0] noise_val;
    reg enable_lfsr;
    
    reg [ADDR_WIDTH-1:0] addr_limit; 
    
    // Generator Noise
    // Pastikan parameter DATA_WIDTH diteruskan dengan benar
    lfsr_noise_gen #(
        .DATA_WIDTH(DATA_WIDTH)
    ) noise_inst (
        .clk(clk),
        .rst_n(rst_n),
        .enable(enable_lfsr),
        .noise_out(noise_val),
        .valid_out(noise_valid)
    );
    
    reg [ADDR_WIDTH-1:0] decoded_limit;
    
    // Decoder ukuran matriks
    always @(*) begin
        case (size)
            3'b000: decoded_limit = 14'd15;    // 4x4
            3'b001: decoded_limit = 14'd63;    // 8x8
            3'b010: decoded_limit = 14'd255;   // 16x16
            3'b011: decoded_limit = 14'd1023;  // 32x32
            3'b100: decoded_limit = 14'd4095;  // 64x64
            3'b101: decoded_limit = 14'd16383; // 128x128
            default: decoded_limit = 14'd16383;
        endcase
    end

    // Handling Range [-2, 2]
    /* CATATAN IMPLEMENTASI:
       Jika format data adalah Fixed Point Q3.13 (1 bit sign, 2 bit integer, 13 bit frac),
       Maka full 16-bit random akan menghasilkan range [-4, 4) secara matematis.
       
       Jika Anda ingin STRICTLY [-2, 2], Anda bisa melakukan right shift (div 2)
       pada output noise, atau memastikan bit MSB ke-2 (integer bit tertinggi) selalu sama dengan bit sign.
       
       Di bawah ini adalah implementasi raw (full range). 
       Jika ingin memperkecil range menjadi setengahnya, ubah assign di bawah:
       assign bram_wdata = {noise_val[DATA_WIDTH-1], noise_val[DATA_WIDTH-1:1]}; // Arithmetic Shift Right
    */
    assign bram_wdata = noise_val; 
    assign bram_we = enable_lfsr && noise_valid; 

    // State Machine
    always @(posedge clk or negedge rst_n) begin
        if (!rst_n) begin
            bram_addr   <= 0;
            enable_lfsr <= 1;
            done        <= 0;
            addr_limit  <= 0;
        end else begin
            // Start logic
            if (start && !enable_lfsr && !done) begin
                bram_addr   <= 0;
                done        <= 0;
                addr_limit  <= decoded_limit; 
            end 
            
            if (enable_lfsr) begin
                if (noise_valid) begin
                    if (bram_addr == addr_limit) begin
                        done        <= 1;
                    end else begin
                        bram_addr   <= bram_addr + 1;
                    end
                end
            end else begin
                if (!start) done <= 0; // Handshake reset
            end
        end
    end

endmodule

noise_generator/tb_noise_filler.v
`include "noise_matrix_filler.v"
module tb_noise_filler #(parameter DATA_WIDTH = 16, parameter ADDR_WIDTH = 14);
    reg  clk;
    reg rst_n;
    reg start;
    reg [2:0] size;
    
    wire [ADDR_WIDTH-1:0] bram_addr;
    wire [DATA_WIDTH-1:0] bram_wdata;
    wire bram_we;           
    wire done;

    noise_matrix_filler #(
        .DATA_WIDTH(DATA_WIDTH),
        .ADDR_WIDTH(ADDR_WIDTH)
    ) uut (
        .clk(clk),
        .rst_n(rst_n),
        .start(start),
        .size(size),
        .bram_addr(bram_addr),
        .bram_wdata(bram_wdata),
        .bram_we(bram_we),           
        .done(done)
    );

    initial begin
        forever #10 clk = ~clk;
    end

    initial begin
        $dumpfile("tb_noise_filler.vcd");
        $dumpvars(0, tb_noise_filler);
        

        clk = 0;
        rst_n = 0;
        start = 0;
        size = 3'b000; // 
        #20;
        rst_n = 1;
        #20;
        start = 1;
        #20;
        start = 0;
        // until done = 1
        // wait (done == 1);
        #1000
        #20;    
        $finish;
    end

endmodule

noise_generator/tb_noise_filler.vcd
$date
	Tue Jan 27 10:29:28 2026
$end
$version
	Icarus Verilog
$end
$timescale
	1ps
$end
$scope module tb_noise_filler $end
$var wire 1 ! done $end
$var wire 1 " bram_we $end
$var wire 16 # bram_wdata [15:0] $end
$var wire 14 $ bram_addr [13:0] $end
$var parameter 32 % ADDR_WIDTH $end
$var parameter 32 & DATA_WIDTH $end
$var reg 1 ' clk $end
$var reg 1 ( rst_n $end
$var reg 3 ) size [2:0] $end
$var reg 1 * start $end
$scope module uut $end
$var wire 16 + bram_wdata [15:0] $end
$var wire 1 " bram_we $end
$var wire 1 ' clk $end
$var wire 1 ( rst_n $end
$var wire 3 , size [2:0] $end
$var wire 1 * start $end
$var wire 1 - noise_valid $end
$var wire 16 . noise_val [15:0] $end
$var parameter 32 / ADDR_WIDTH $end
$var parameter 32 0 DATA_WIDTH $end
$var reg 14 1 addr_limit [13:0] $end
$var reg 14 2 bram_addr [13:0] $end
$var reg 14 3 decoded_limit [13:0] $end
$var reg 1 ! done $end
$var reg 1 4 enable_lfsr $end
$scope module noise_inst $end
$var wire 1 ' clk $end
$var wire 1 4 enable $end
$var wire 1 ( rst_n $end
$var wire 16 5 noise_out [15:0] $end
$var parameter 32 6 DATA_WIDTH $end
$var parameter 32 7 POLY_MASK $end
$var parameter 32 8 SEED $end
$var reg 32 9 r_lfsr [31:0] $end
$var reg 1 - valid_out $end
$scope begin genblk1 $end
$upscope $end
$upscope $end
$upscope $end
$upscope $end
$enddefinitions $end
$comment Show the parameter values. $end
$dumpall
b10101100111000010010001101000101 8
b10000000001000000000000000000011 7
b10000 6
b10000 0
b1110 /
b10000 &
b1110 %
$end
#0
$dumpvars
b10101100111000010010001101000101 9
b1010110011100001 5
14
b1111 3
b0 2
b0 1
b1010110011100001 .
0-
b0 ,
b1010110011100001 +
0*
b0 )
0(
0'
b0 $
b1010110011100001 #
0"
0!
$end
#10000
1'
#20000
0'
1(
#30000
b1101011001010000 #
b1101011001010000 +
b1101011001010000 .
b1101011001010000 5
1"
b11010110010100001001000110100001 9
1-
1'
#40000
0'
1*
#50000
b1110101100001000 #
b1110101100001000 +
b1110101100001000 .
b1110101100001000 5
1!
b11101011000010000100100011010011 9
1'
#60000
0'
0*
#70000
b1111010110100100 #
b1111010110100100 +
b1111010110100100 .
b1111010110100100 5
b11110101101001000010010001101010 9
1'
#80000
0'
#90000
b111101011010010 #
b111101011010010 +
b111101011010010 .
b111101011010010 5
b1111010110100100001001000110101 9
1'
#100000
0'
#110000
b1011110101001001 #
b1011110101001001 +
b1011110101001001 .
b1011110101001001 5
b10111101010010010000100100011001 9
1'
#120000
0'
#130000
b1101111010000100 #
b1101111010000100 +
b1101111010000100 .
b1101111010000100 5
b11011110100001001000010010001111 9
1'
#140000
0'
#150000
b1110111101100010 #
b1110111101100010 +
b1110111101100010 .
b1110111101100010 5
b11101111011000100100001001000100 9
1'
#160000
0'
#170000
b111011110110001 #
b111011110110001 +
b111011110110001 .
b111011110110001 5
b1110111101100010010000100100010 9
1'
#180000
0'
#190000
b11101111011000 #
b11101111011000 +
b11101111011000 .
b11101111011000 5
b111011110110001001000010010001 9
1'
#200000
0'
#210000
b1001110111001100 #
b1001110111001100 +
b1001110111001100 .
b1001110111001100 5
b10011101110011000100100001001011 9
1'
#220000
0'
#230000
b1100111011000110 #
b1100111011000110 +
b1100111011000110 .
b1100111011000110 5
b11001110110001100010010000100110 9
1'
#240000
0'
#250000
b110011101100011 #
b110011101100011 +
b110011101100011 .
b110011101100011 5
b1100111011000110001001000010011 9
1'
#260000
0'
#270000
b1011001110010001 #
b1011001110010001 +
b1011001110010001 .
b1011001110010001 5
b10110011100100011000100100001010 9
1'
#280000
0'
#290000
b101100111001000 #
b101100111001000 +
b101100111001000 .
b101100111001000 5
b1011001110010001100010010000101 9
1'
#300000
0'
#310000
b1010110011000100 #
b1010110011000100 +
b1010110011000100 .
b1010110011000100 5
b10101100110001000110001001000001 9
1'
#320000
0'
#330000
b1101011001000010 #
b1101011001000010 +
b1101011001000010 .
b1101011001000010 5
b11010110010000100011000100100011 9
1'
#340000
0'
#350000
b1110101100000001 #
b1110101100000001 +
b1110101100000001 .
b1110101100000001 5
b11101011000000010001100010010010 9
1'
#360000
0'
#370000
b111010110000000 #
b111010110000000 +
b111010110000000 .
b111010110000000 5
b1110101100000001000110001001001 9
1'
#380000
0'
#390000
b1011101011100000 #
b1011101011100000 +
b1011101011100000 .
b1011101011100000 5
b10111010111000000100011000100111 9
1'
#400000
0'
#410000
b1101110101010000 #
b1101110101010000 +
b1101110101010000 .
b1101110101010000 5
b11011101010100000010001100010000 9
1'
#420000
0'
#430000
b110111010101000 #
b110111010101000 +
b110111010101000 .
b110111010101000 5
b1101110101010000001000110001000 9
1'
#440000
0'
#450000
b11011101010100 #
b11011101010100 +
b11011101010100 .
b11011101010100 5
b110111010101000000100011000100 9
1'
#460000
0'
#470000
b1101110101010 #
b1101110101010 +
b1101110101010 .
b1101110101010 5
b11011101010100000010001100010 9
1'
#480000
0'
#490000
b110111010101 #
b110111010101 +
b110111010101 .
b110111010101 5
b1101110101010000001000110001 9
1'
#500000
0'
#510000
b1000011011001010 #
b1000011011001010 +
b1000011011001010 .
b1000011011001010 5
b10000110110010101000000100011011 9
1'
#520000
0'
#530000
b1100001101000101 #
b1100001101000101 +
b1100001101000101 .
b1100001101000101 5
b11000011010001010100000010001110 9
1'
#540000
0'
#550000
b110000110100010 #
b110000110100010 +
b110000110100010 .
b110000110100010 5
b1100001101000101010000001000111 9
1'
#560000
0'
#570000
b1011000011110001 #
b1011000011110001 +
b1011000011110001 .
b1011000011110001 5
b10110000111100010101000000100000 9
1'
#580000
0'
#590000
b101100001111000 #
b101100001111000 +
b101100001111000 .
b101100001111000 5
b1011000011110001010100000010000 9
1'
#600000
0'
#610000
b10110000111100 #
b10110000111100 +
b10110000111100 .
b10110000111100 5
b101100001111000101010000001000 9
1'
#620000
0'
#630000
b1011000011110 #
b1011000011110 +
b1011000011110 .
b1011000011110 5
b10110000111100010101000000100 9
1'
#640000
0'
#650000
b101100001111 #
b101100001111 +
b101100001111 .
b101100001111 5
b1011000011110001010100000010 9
1'
#660000
0'
#670000
b10110000111 #
b10110000111 +
b10110000111 .
b10110000111 5
b101100001111000101010000001 9
1'
#680000
0'
#690000
b1000001011100011 #
b1000001011100011 +
b1000001011100011 .
b1000001011100011 5
b10000010111000111100010101000011 9
1'
#700000
0'
#710000
b1100000101010001 #
b1100000101010001 +
b1100000101010001 .
b1100000101010001 5
b11000001010100011110001010100010 9
1'
#720000
0'
#730000
b110000010101000 #
b110000010101000 +
b110000010101000 .
b110000010101000 5
b1100000101010001111000101010001 9
1'
#740000
0'
#750000
b1011000001110100 #
b1011000001110100 +
b1011000001110100 .
b1011000001110100 5
b10110000011101000111100010101011 9
1'
#760000
0'
#770000
b1101100000011010 #
b1101100000011010 +
b1101100000011010 .
b1101100000011010 5
b11011000000110100011110001010110 9
1'
#780000
0'
#790000
b110110000001101 #
b110110000001101 +
b110110000001101 .
b110110000001101 5
b1101100000011010001111000101011 9
1'
#800000
0'
#810000
b1011011000100110 #
b1011011000100110 +
b1011011000100110 .
b1011011000100110 5
b10110110001001101000111100010110 9
1'
#820000
0'
#830000
b101101100010011 #
b101101100010011 +
b101101100010011 .
b101101100010011 5
b1011011000100110100011110001011 9
1'
#840000
0'
#850000
b1010110110101001 #
b1010110110101001 +
b1010110110101001 .
b1010110110101001 5
b10101101101010011010001111000110 9
1'
#860000
0'
#870000
b101011011010100 #
b101011011010100 +
b101011011010100 .
b101011011010100 5
b1010110110101001101000111100011 9
1'
#880000
0'
#890000
b1010101101001010 #
b1010101101001010 +
b1010101101001010 .
b1010101101001010 5
b10101011010010100110100011110010 9
1'
#900000
0'
#910000
b101010110100101 #
b101010110100101 +
b101010110100101 .
b101010110100101 5
b1010101101001010011010001111001 9
1'
#920000
0'
#930000
b1010101011110010 #
b1010101011110010 +
b1010101011110010 .
b1010101011110010 5
b10101010111100101001101000111111 9
1'
#940000
0'
#950000
b1101010101011001 #
b1101010101011001 +
b1101010101011001 .
b1101010101011001 5
b11010101010110010100110100011100 9
1'
#960000
0'
#970000
b110101010101100 #
b110101010101100 +
b110101010101100 .
b110101010101100 5
b1101010101011001010011010001110 9
1'
#980000
0'
#990000
b11010101010110 #
b11010101010110 +
b11010101010110 .
b11010101010110 5
b110101010101100101001101000111 9
1'
#1000000
0'
#1010000
b1001101010001011 #
b1001101010001011 +
b1001101010001011 .
b1001101010001011 5
b10011010100010110010100110100000 9
1'
#1020000
0'
#1030000
b100110101000101 #
b100110101000101 +
b100110101000101 .
b100110101000101 5
b1001101010001011001010011010000 9
1'
#1040000
0'
#1050000
b10011010100010 #
b10011010100010 +
b10011010100010 .
b10011010100010 5
b100110101000101100101001101000 9
1'
#1060000
0'
#1070000
b1001101010001 #
b1001101010001 +
b1001101010001 .
b1001101010001 5
b10011010100010110010100110100 9
1'
