upsampling/upsampling2/reg_output.v
module reg_output #(parameter length = 16)

(
    input wire clk,
    input wire rst,
    input wire [3:0] write_mode,
    
    input wire row_even,
    input wire coloumn_even,
    input wire [7:0] kolom,

    input wire [length-1:0] data_in1,
    input wire [length-1:0] data_in2,
    input wire [length-1:0] data_in3,
    input wire [length-1:0] data_in4,

    input wire [length-1:0] data_in5,
    input wire [length-1:0] data_in6,
    input wire [length-1:0] data_in7,
    input wire [length-1:0] data_in8,
    input wire [length-1:0] data_in9,

    output reg [length-1:0] dout
);
    reg [length-1:0] temp_dout [0:127];

    always @(*) begin

        case (write_mode)

                    4'b0000 : begin
                        dout = data_in9;
                    end

                    4'b0001 : begin
                        // if coloumn_even, dout = data_in5 else data_in6
                        dout = coloumn_even ? data_in6 : data_in5;
                    end

                    4'b0010 : begin
                        dout = data_in9;
                    end

                    4'b0011 : begin
                        dout = row_even ? data_in7 : temp_dout[kolom];
                        
                    end

                    4'b0100 : begin

                        if (coloumn_even == 1'b0) begin
                            if (row_even == 1'b1) begin
                                dout = data_in1;
                            end else begin
                                dout = temp_dout[kolom];
                            end
                        end else begin
                            if (row_even == 1'b1) begin
                                dout = data_in2;
                            end else begin
                                dout = temp_dout[kolom];
                            end
                        end
                        
                    end

                    4'b0101 : begin
                        dout = row_even ? data_in7 : temp_dout[kolom];

                    end

                    4'b0110 : begin
                        dout = data_in9;
                    end


                    4'b0111 : begin
                        dout = coloumn_even ? data_in6 : data_in5;
                    end

                    4'b1000 : begin
                        dout = data_in9;
                    end

                default : begin
                        // do nothing
                    end

                endcase;
        

    end

    always @(posedge clk) begin
        if (!rst) begin
            temp_dout[0] <= 0;
        end else begin
            case (write_mode) 

            4'b0100 : begin
            if (coloumn_even == 1'b0) begin
                    temp_dout[kolom] <= data_in3;
                    end

            else begin
                    temp_dout[kolom] <= data_in4;
                end
            end

            default : begin
                temp_dout[kolom] <= data_in8;

            end

            endcase
        end

    end


endmodule;

upsampling/upsampling2/tb_reg_output.v
`timescale 1ns / 1ps
`include "reg_output.v"

module tb_reg_output;

    // Parameter
    parameter length = 16;

    // Inputs (Regs in Testbench)
    reg clk;
    reg rst;
    reg [3:0] write_mode;
    reg row_even;
    reg [length-1:0] data_in1;
    reg [length-1:0] data_in2;
    reg [length-1:0] data_in3;
    reg [length-1:0] data_in4;
    reg [length-1:0] data_in5;
    reg [length-1:0] data_in6;
    reg [length-1:0] data_in7;
    reg [length-1:0] data_in8;
    reg [length-1:0] data_in9;

    // Outputs (Wires in Testbench)
    wire [length-1:0] dout;

    // Loop variable
    integer i;

    // Instantiate the Unit Under Test (UUT)
    reg_output #(
        .length(length)
    ) uut (
        .clk(clk), 
        .rst(rst), 
        .write_mode(write_mode), 
        .row_even(row_even), 
        .data_in1(data_in1), 
        .data_in2(data_in2), 
        .data_in3(data_in3), 
        .data_in4(data_in4), 
        .data_in5(data_in5), 
        .data_in6(data_in6), 
        .data_in7(data_in7), 
        .data_in8(data_in8), 
        .data_in9(data_in9), 
        .dout(dout)
    );

    // Clock Generation (Period = 10ns)
    initial begin
        clk = 0;
        forever #5 clk = ~clk;
    end

    // Stimulus Process
    initial begin
        $dumpfile("tb_out.vcd");
        $dumpvars(0, tb_reg_output);

        // 1. Initialize Inputs
        rst = 0; // Active low reset asserted initially
        write_mode = 0;
        row_even = 0;

        // Set Data Inputs 1..9
        data_in1 = 16'd1;
        data_in2 = 16'd2;
        data_in3 = 16'd3;
        data_in4 = 16'd4;
        data_in5 = 16'd5;
        data_in6 = 16'd6;
        data_in7 = 16'd7;
        data_in8 = 16'd8;
        data_in9 = 16'd9;

        // 2. Apply Reset
        #20;
        rst = 1; // Release reset (active low)
        
        // Tunggu sebentar agar sinyal stabil
        @(negedge clk);

        // 3. Loop through all write_modes (0 to 8)
        // Note: Logic case kamu menghandle 0 sampai 8 (4'b1000)
        for (i = 0; i <= 8; i = i + 1) begin
            
            // Set Write Mode
            write_mode = i;
            
            // --- Cycle 1 & 2: Row Even = 0 ---
            // Kita tunggu 2 cycle agar internal register 'coloumn_even' sempat toggle (0->1 atau 1->0)
            row_even = 0;
            repeat (2) @(posedge clk); 

            // --- Cycle 3 & 4: Row Even = 1 ---
            // Kita tunggu 2 cycle lagi dengan row_even aktif
            row_even = 1;
            repeat (2) @(posedge clk);
            
            // Total durasi per write_mode = 4 clock cycles
        end

        // 4. Finish Simulation
        #20;
        $display("Testbench Completed Successfully.");
        $finish;
    end

    // Optional: Monitor changes to console
    initial begin
        $monitor("Time=%0t | Mode=%b | RowEven=%b | coloumn_even_Internal=%b | Dout=%d", 
                 $time, write_mode, row_even, uut.coloumn_even, dout);
    end

endmodule

// 1 1 1 1 1 1 1 1 
// 1 1 1 1 1 1 1 1
// 1 1 1 1 1 1 1 1

upsampling/upsampling2/tb_out.vcd
$date
	Tue Jan 20 17:09:29 2026
$end
$version
	Icarus Verilog
$end
$timescale
	1ps
$end
$scope module tb_reg_output $end
$var wire 16 ! dout [15:0] $end
$var parameter 32 " length $end
$var reg 1 # clk $end
$var reg 16 $ data_in1 [15:0] $end
$var reg 16 % data_in2 [15:0] $end
$var reg 16 & data_in3 [15:0] $end
$var reg 16 ' data_in4 [15:0] $end
$var reg 16 ( data_in5 [15:0] $end
$var reg 16 ) data_in6 [15:0] $end
$var reg 16 * data_in7 [15:0] $end
$var reg 16 + data_in8 [15:0] $end
$var reg 16 , data_in9 [15:0] $end
$var reg 1 - row_even $end
$var reg 1 . rst $end
$var reg 4 / write_mode [3:0] $end
$var integer 32 0 i [31:0] $end
$scope module uut $end
$var wire 1 # clk $end
$var wire 1 1 coloumn_even $end
$var wire 16 2 data_in1 [15:0] $end
$var wire 16 3 data_in2 [15:0] $end
$var wire 16 4 data_in3 [15:0] $end
$var wire 16 5 data_in4 [15:0] $end
$var wire 16 6 data_in5 [15:0] $end
$var wire 16 7 data_in6 [15:0] $end
$var wire 16 8 data_in7 [15:0] $end
$var wire 16 9 data_in8 [15:0] $end
$var wire 16 : data_in9 [15:0] $end
$var wire 8 ; kolom [7:0] $end
$var wire 1 - row_even $end
$var wire 1 . rst $end
$var wire 4 < write_mode [3:0] $end
$var parameter 32 = length $end
$var reg 16 > dout [15:0] $end
$upscope $end
$upscope $end
$enddefinitions $end
$comment Show the parameter values. $end
$dumpall
b10000 =
b10000 "
$end
#0
$dumpvars
b1001 >
b0 <
bz ;
b1001 :
b1000 9
b111 8
b110 7
b101 6
b100 5
b11 4
b10 3
b1 2
z1
bx 0
b0 /
0.
0-
b1001 ,
b1000 +
b111 *
b110 )
b101 (
b100 '
b11 &
b10 %
b1 $
0#
b1001 !
$end
#5000
1#
#10000
0#
#15000
1#
#20000
b0 0
0#
1.
#25000
1#
#30000
0#
#35000
1-
1#
#40000
0#
#45000
1#
#50000
0#
#55000
b1xx !
b1xx >
0-
b1 /
b1 <
b1 0
1#
#60000
0#
#65000
1#
#70000
0#
#75000
1-
1#
#80000
0#
#85000
1#
#90000
0#
#95000
b1001 !
b1001 >
0-
b10 /
b10 <
b10 0
1#
#100000
0#
#105000
1#
#110000
0#
#115000
1-
1#
#120000
0#
#125000
1#
#130000
0#
#135000
b1000 !
b1000 >
0-
b11 /
b11 <
b11 0
1#
#140000
0#
#145000
1#
#150000
0#
#155000
b111 !
b111 >
1-
1#
#160000
0#
#165000
1#
#170000
0#
#175000
bx !
bx >
0-
b100 /
b100 <
b100 0
1#
#180000
0#
#185000
1#
#190000
0#
#195000
b10 !
b10 >
1-
1#
#200000
0#
#205000
1#
#210000
0#
#215000
b1000 !
b1000 >
0-
b101 /
b101 <
b101 0
1#
#220000
0#
#225000
1#
#230000
0#
#235000
b111 !
b111 >
1-
1#
#240000
0#
#245000
1#
#250000
0#
#255000
b1001 !
b1001 >
0-
b110 /
b110 <
b110 0
1#
#260000
0#
#265000
1#
#270000
0#
#275000
1-
1#
#280000
0#
#285000
1#
#290000
0#
#295000
b1xx !
b1xx >
0-
b111 /
b111 <
b111 0
1#
#300000
0#
#305000
1#
#310000
0#
#315000
1-
1#
#320000
0#
#325000
1#
#330000
0#
#335000
b1001 !
b1001 >
0-
b1000 /
b1000 <
b1000 0
1#
#340000
0#
#345000
1#
#350000
0#
#355000
1-
1#
#360000
0#
#365000
1#
#370000
0#
#375000
b1001 0
1#
